<?xml version="1.0" encoding="UTF-8"?>
<objects serializationModel="Studio.02.02.00">
	<object class="AudioFile" id="{6876c0fb-7ba3-4bde-98c4-9185b52075a0}">
		<property name="assetPath">
			<value>In_Game/NPC/Enemies/DEATH/ENEMY_DEATH_UF_4.wav</value>
		</property>
		<property name="frequencyInKHz">
			<value>48</value>
		</property>
		<property name="channelCount">
			<value>2</value>
		</property>
		<property name="length">
			<value>2.625</value>
		</property>
		<relationship name="masterAssetFolder">
			<destination>{61399258-5a91-4f72-86f0-c1ca9efe25aa}</destination>
		</relationship>
	</object>
</objects>
